extended_filters/__init__.py
extended_filters/filters.py
extended_filters/forms.py
extended_filters/urls.py
extended_filters/views.py
extended_filters/locale/ru/LC_MESSAGES/django.mo
extended_filters/locale/ru/LC_MESSAGES/django.po
extended_filters/static/extended_filters/css/autocomplete_filters.css
extended_filters/static/extended_filters/js/autocomplete_script.js
extended_filters/static/extended_filters/js/scripts.js
extended_filters/templates/extended_filters/autocomplete_filter.html
extended_filters/templates/extended_filters/checkbox_filter.html
extended_filters/templates/extended_filters/date_range_filter.html
extended_filters/templates/extended_filters/filter.html
django_extended_filters-0.7.dist-info/METADATA
django_extended_filters-0.7.dist-info/WHEEL
django_extended_filters-0.7.dist-info/top_level.txt
django_extended_filters-0.7.dist-info/RECORD
